measure_dist/__init__.py
measure_dist/_measure_dist.cpython-310-x86_64-linux-gnu.h
measure_dist/_measure_dist.cpython-310-x86_64-linux-gnu.so
measure_dist/_measure_dist.cpython-36m-x86_64-linux-gnu.h
measure_dist/_measure_dist.cpython-36m-x86_64-linux-gnu.so
measure_dist/build.py
measure_dist/go.py
measure_dist/measure_dist.c
measure_dist/measure_dist.go
measure_dist/measure_dist.py
measure_dist/measure_dist_go.h
measure_dist-1.1.0.post4.dist-info/LICENSE
measure_dist-1.1.0.post4.dist-info/METADATA
measure_dist-1.1.0.post4.dist-info/WHEEL
measure_dist-1.1.0.post4.dist-info/top_level.txt
measure_dist-1.1.0.post4.dist-info/RECORD
