Metadata-Version: 2.1
Name: measure-dist
Version: 1.1.0.post4
Summary: Measurement helper functions
Author: Gegeco
Author-email: Gegeco <gegeco06@gmail.com>
License: MIT License
Project-URL: Homepage, https://github.com/gegeco/measure_dist
Keywords: Measure,Measurement,Distance
Classifier: License :: OSI Approved :: MIT License
Classifier: Programming Language :: Python :: 3
Requires-Python: >3.5,<3.11,!=3.7.*,!=3.8.*,!=3.9.*
License-File: LICENSE
Requires-Dist: pybindgen
